{
    "title": "Evening Boat Ride on Lake Llanquihue beneath the Iconic Osorno Volcano in Puerto Varas",
    "description": "Puerto Varas, Los Lagos Region, Chile: A serene evening unfolds across the vast, glass-like surface of Lake Llanquihue as a small boat traverses the tranquil waters toward the horizon. The iconic, snow-capped Osorno Volcano commands the center of the frame, bathed in the soft, ethereal hues of a fading pastel sunset. Foreground rocks along the shoreline provide a textured anchor to the composition, leading the eye toward the distant, symmetrical volcanic peak. Cool blue shadows settle over the volcanic sand beach, contrasting beautifully with the warm, peach-colored glow lingering in the atmosphere. The gentle ripples left in the wake of the boat disturb the mirror-like reflections, adding a sense of movement to the otherwise meditative landscape. Silence seems to permeate the air, creating a moment of profound stillness that defines the glacial beauty of the Chilean Lake District. As the last remnants of daylight disappear behind the Andes, the world feels remarkably quiet and vast. This landscape serves as a testament to the dramatic volcanic geography that has shaped the cultural and environmental heritage of Southern Chile. Such vistas highlight the unique intersection of untamed wilderness and accessible travel experiences found within this picturesque region. This image is a collaborative production by Samuel Jeffery and Audrey Bergner for Samuel and Audrey. \n\n---\n\n Puerto Varas, Región de Los Lagos, Chile: Un atardecer sereno se despliega sobre la vasta superficie cristalina del Lago Llanquihue mientras una pequeña embarcación atraviesa las aguas tranquilas hacia el horizonte. El icónico Volcán Osorno, coronado de nieve, domina el centro de la imagen, bañado por los tonos suaves y etéreos de un ocaso pastel. Las rocas en primer plano a lo largo de la orilla ofrecen un ancla texturizada a la composición, guiando la mirada hacia la cima volcánica simétrica y distante. Las sombras azules se asientan sobre la playa de arena volcánica, contrastando hermosamente con el resplandor cálido y rosado que permanece en la atmósfera. Las suaves ondas dejadas por la estela del barco perturban los reflejos como espejo, añadiendo una sensación de movimiento a un paisaje por lo demás meditativo. El silencio parece permear el aire, creando un momento de profunda quietud que define la belleza glacial de la Región de los Lagos. A medida que los últimos restos de luz diurna desaparecen tras los Andes, el mundo se siente notablemente tranquilo y vasto. Este paisaje sirve como testimonio de la dramática geografía volcánica que ha moldeado el patrimonio cultural y medioambiental del sur de Chile. Estas vistas destacan la intersección única entre la naturaleza indómita y las experiencias de viaje accesibles que se encuentran en esta pintoresca región. Esta imagen es una producción colaborativa de Samuel Jeffery y Audrey Bergner para Samuel and Audrey.",
    "tags": [
        "Puerto Varas",
        "Lake Llanquihue",
        "Osorno Volcano",
        "Chile",
        "Patagonia",
        "Chilean Lake District",
        "Los Lagos",
        "Volcano",
        "Sunset",
        "Travel Photography",
        "Landscape",
        "South America",
        "Andes Mountains",
        "Volcanic Landscape",
        "Glacial Lake",
        "Reflection",
        "Boat",
        "Outdoor Adventure",
        "Nature",
        "Travel Documentation",
        "Southern Hemisphere",
        "Scenic View",
        "Waterfront",
        "Pacific Rim",
        "Tourism",
        "Patagonian Landscapes",
        "Iconic Landmarks",
        "Dusk",
        "Golden Hour",
        "Photography",
        "Nature Photography",
        "Volcanology",
        "Travel Content",
        "Geographic Beauty",
        "Chilean Culture",
        "Wilderness",
        "Lake Scenery",
        "Outdoor Lifestyle",
        "Destination Chile",
        "Visual Storytelling",
        "Travel Bloggers",
        "Scenic Travel",
        "Ethereal Lighting",
        "Remote Landscapes",
        "Earth Science",
        "Andean Peaks",
        "Water Travel",
        "Tranquility",
        "Exploration",
        "Nomadic Life"
    ],
    "json_ld": {
        "@context": "https://schema.org",
        "@type": "ImageObject",
        "creator": [
            {
                "@type": "Person",
                "name": "Samuel Jeffery",
                "sameAs": [
                    "https://samueljeffery.net",
                    "https://audreybergner.com",
                    "https://samuelandaudrey.com",
                    "https://thatbackpacker.com",
                    "https://nomadicsamuel.com",
                    "https://youtube.com/@samuelandaudrey",
                    "https://youtube.com/@samuelyaudrey"
                ]
            },
            {
                "@type": "Person",
                "name": "Audrey Bergner",
                "sameAs": [
                    "https://samueljeffery.net",
                    "https://audreybergner.com",
                    "https://samuelandaudrey.com",
                    "https://thatbackpacker.com",
                    "https://nomadicsamuel.com",
                    "https://youtube.com/@samuelandaudrey",
                    "https://youtube.com/@samuelyaudrey"
                ]
            }
        ]
    }
}