{
    "title": "Abandoned Wooden Pier in Punta Arenas Chile Patagonia Featuring Resilient Imperial Cormorant Bird Colonies",
    "description": "Punta Arenas, Magallanes: An aged, decaying wooden pier stretches boldly into the deep blue expanse of the Strait of Magellan. Weathered timber planks and structural pilings display a rough, textured patina earned from decades of exposure to harsh sub-Antarctic winds. Perched atop the remaining skeleton of the structure, a vast colony of Imperial Cormorants claims the space as their private island sanctuary. The sharp focus on the foreground timbers draws the eye toward the distant horizon, where the sea meets a hazy, overcast sky. Soft, natural daylight illuminates the stark contrast between the decaying human-made architecture and the vibrant, living wildlife. This scene captures the quiet resilience of Patagonia, where remnants of early maritime trade are reclaimed by the natural coastal ecosystem. The rhythmic lapping of the cold water against the wooden beams creates a sensory experience that feels both solitary and alive with avian activity. Documenting these structural ruins offers a profound look at how human infrastructure interacts with the rugged wilderness of the southern extreme. Observing the interaction between historical maritime relics and the thriving local seabird populations is essential for understanding the unique ecological and historical identity of this remote Chilean frontier. This image is a collaborative production by Samuel Jeffery and Audrey Bergner for Samuel and Audrey Media Network. \n\n---\n\n Punta Arenas, Magallanes: Un antiguo muelle de madera en ruinas se extiende audazmente hacia la profunda extensión azul del Estrecho de Magallanes. Los tablones de madera desgastados y los pilotes estructurales muestran una pátina rugosa y texturizada ganada tras décadas de exposición a los fuertes vientos subantárticos. Posada sobre el esqueleto restante de la estructura, una vasta colonia de cormoranes imperiales reclama el espacio como su santuario isleño privado. El enfoque nítido en las maderas del primer plano dirige la mirada hacia el horizonte distante, donde el mar se encuentra con un cielo brumoso y nublado. La luz natural suave ilumina el marcado contraste entre la arquitectura humana en decadencia y la vibrante fauna viviente. Esta escena captura la tranquila resiliencia de la Patagonia, donde los restos del comercio marítimo temprano son reclamados por el ecosistema costero natural. El rítmico chapoteo del agua fría contra las vigas de madera crea una experiencia sensorial que se siente a la vez solitaria y llena de actividad aviar. Documentar estas ruinas estructurales ofrece una mirada profunda a cómo la infraestructura humana interactúa con la naturaleza salvaje del extremo sur. Observar la interacción entre las reliquias marítimas históricas y las prósperas poblaciones locales de aves marinas es esencial para comprender la identidad ecológica e histórica única de esta remota frontera chilena. Esta imagen es una producción colaborativa de Samuel Jeffery y Audrey Bergner para Samuel and Audrey Media Network.",
    "tags": [
        "PuntaArenas",
        "Magallanes",
        "Chile",
        "Patagonia",
        "StraitOfMagellan",
        "ImperialCormorant",
        "MaritimeHistory",
        "AbandonedPier",
        "WoodenArchitecture",
        "CoastalLandscape",
        "WildlifePhotography",
        "SouthAmerica",
        "ChileanTravel",
        "BirdColony",
        "OceanView",
        "PatagonianCoast",
        "Seabirds",
        "HistoricalRemnants",
        "TravelPhotography",
        "NaturePhotography",
        "RemoteDestinations",
        "SubAntarctic",
        "MarineEcosystem",
        "ArchitecturePhotography",
        "LandscapePhotography",
        "WeatheredWood",
        "CulturalHeritage",
        "MaritimeHeritage",
        "SouthChile",
        "ScenicView",
        "Wilderness",
        "CoastalEcology",
        "Birdwatching",
        "Exploration",
        "Geography",
        "TravelMedia",
        "OutdoorAdventure",
        "WeatheredTextures",
        "PacificCoast",
        "SouthernCone",
        "RegionalIdentity",
        "EnvironmentalArt",
        "Seascape",
        "RawBeauty",
        "RusticCharm",
        "HistoryOfChile",
        "CoastalLife",
        "RemoteFrontier",
        "NatureStudies",
        "SamuelAndAudrey"
    ],
    "json_ld": {
        "@context": "https://schema.org",
        "@type": "ImageObject",
        "creator": [
            {
                "@type": "Person",
                "name": "Samuel Jeffery",
                "sameAs": [
                    "https://samueljeffery.net",
                    "https://audreybergner.com",
                    "https://samuelandaudrey.com",
                    "https://thatbackpacker.com",
                    "https://nomadicsamuel.com",
                    "https://youtube.com/@samuelandaudrey",
                    "https://youtube.com/@samuelyaudrey"
                ]
            },
            {
                "@type": "Person",
                "name": "Audrey Bergner",
                "sameAs": [
                    "https://samueljeffery.net",
                    "https://audreybergner.com",
                    "https://samuelandaudrey.com",
                    "https://thatbackpacker.com",
                    "https://nomadicsamuel.com",
                    "https://youtube.com/@samuelandaudrey",
                    "https://youtube.com/@samuelyaudrey"
                ]
            }
        ]
    }
}