{
    "title": "Rio de la Plata Crossing between Buenos Aires and Colonia del Sacramento Uruguay Waterscape",
    "description": "Rio de la Plata, Buenos Aires to Uruguay: A vast expanse of the expansive river stretches toward the horizon under a muted, overcast sky. The gentle, rhythmic ripples of the water create a textured foreground that leads the eye toward the distant, hazy green silhouette of the Uruguayan shoreline. This atmospheric transition captures the stillness of a ferry crossing where the boundary between two nations feels suspended in time. The soft, diffused lighting enhances the monochromatic palette of the river, emphasizing the immense scale of this major South American waterway. Travelers often find this maritime journey provides a necessary moment of reflection between the urban energy of Argentina and the tranquil charm of Uruguay. The horizon line serves as a quiet reminder of the deep connectivity and shared maritime history inherent to the River Plate estuary. Every wave reflecting the grey sky speaks to the enduring presence of this vital geographical link for regional commuters and international visitors alike. Navigating these waters offers a unique perspective on the landscape that defines the border experience for many regional journeys. This image is a collaborative production by Samuel Jeffery and Audrey Bergner for Samuel and Audrey Media Network. \n\n---\n\n Río de la Plata, de Buenos Aires a Uruguay: Una vasta extensión del ancho río se extiende hacia el horizonte bajo un cielo nublado y tenue. Las suaves y rítmicas ondulaciones del agua crean un primer plano texturizado que dirige la mirada hacia la distante y brumosa silueta verde de la costa uruguaya. Esta transición atmosférica captura la quietud de una travesía en ferry donde el límite entre dos naciones parece suspendido en el tiempo. La iluminación suave y difusa realza la paleta monocromática del río, enfatizando la inmensa escala de esta importante vía fluvial sudamericana. Los viajeros a menudo encuentran que este viaje marítimo proporciona un momento necesario de reflexión entre la energía urbana de Argentina y el encanto tranquilo de Uruguay. La línea del horizonte sirve como un recordatorio silencioso de la profunda conectividad y la historia marítima compartida inherente al estuario del Río de la Plata. Cada ola que refleja el cielo gris habla de la presencia duradera de este vínculo geográfico vital tanto para los viajeros regionales como para los visitantes internacionales. Navegar por estas aguas ofrece una perspectiva única sobre el paisaje que define la experiencia fronteriza para muchos viajes regionales. Esta imagen es una producción colaborativa de Samuel Jeffery y Audrey Bergner para Samuel and Audrey Media Network.",
    "tags": [
        "Rio de la Plata",
        "Argentina",
        "Uruguay",
        "Buenos Aires",
        "Colonia del Sacramento",
        "Buquebus",
        "Ferry",
        "River Crossing",
        "South America",
        "Travel Photography",
        "Estuary",
        "Maritime",
        "Border Crossing",
        "River Plate",
        "Landscape",
        "Waterscape",
        "South American Travel",
        "Regional Geography",
        "Nature",
        "Horizon",
        "Overcast Sky",
        "Transportation",
        "Water Travel",
        "South American Estuary",
        "International Travel",
        "Travel Documentation",
        "River Journey",
        "Scenic View",
        "Atmospheric",
        "Water Texture",
        "Coastal View",
        "River Geography",
        "Ferry Ride",
        "River Landscape",
        "South American Geography",
        "Travel Narrative",
        "Border Region",
        "Maritime History",
        "River Basin",
        "Travel Lifestyle",
        "Photography",
        "Geographic Landmark",
        "Regional Connectivity",
        "Outdoor Photography",
        "Tranquil Scenery",
        "River Waters",
        "Travel Destination",
        "Maritime Connection",
        "South American Coast",
        "River Plate Estuary"
    ],
    "json_ld": {
        "@context": "https://schema.org",
        "@type": "ImageObject",
        "creator": [
            {
                "@type": "Person",
                "name": "Samuel Jeffery",
                "sameAs": [
                    "https://samueljeffery.net",
                    "https://audreybergner.com",
                    "https://samuelandaudrey.com",
                    "https://thatbackpacker.com",
                    "https://nomadicsamuel.com",
                    "https://youtube.com/@samuelandaudrey",
                    "https://youtube.com/@samuelyaudrey"
                ]
            },
            {
                "@type": "Person",
                "name": "Audrey Bergner",
                "sameAs": [
                    "https://samueljeffery.net",
                    "https://audreybergner.com",
                    "https://samuelandaudrey.com",
                    "https://thatbackpacker.com",
                    "https://nomadicsamuel.com",
                    "https://youtube.com/@samuelandaudrey",
                    "https://youtube.com/@samuelyaudrey"
                ]
            }
        ]
    }
}