{
    "title": "Jagged Andes Peaks Over Lake Nahuel Huapi in the Bariloche Region Argentina Landscape",
    "description": "Lake Nahuel Huapi, Río Negro: The rugged Andean range towers majestically above the shimmering turquoise waters, illustrating the dramatic topography of the Patagonian lake district. Sunlight rakes across the sheer, gray stone faces, highlighting the intricate geological textures that define the region's immense vertical scale. Below the rocky summits, a dense, emerald-hued temperate rainforest clings to the steep slopes, creating a striking visual contrast between barren rock and vibrant vegetation. The crystal-clear sky provides a vast, azure backdrop that emphasizes the pristine nature of this protected biosphere. Captured with a high-resolution perspective, the composition allows the viewer to appreciate the quiet, powerful solitude inherent to the Andes mountain range. Shadows trace the deep gullies carved into the cliffs, suggesting a landscape shaped by millennia of glacial activity and seasonal runoff. As one traverses this iconic corridor, the sheer magnitude of the mountain peaks reminds travelers of the raw, untouched beauty preserved within these southern latitudes. This scene serves as a testament to the geographic grandeur that defines the Argentine Patagonia, offering a window into the serene environment found during a classic lake crossing. The interplay of light and shadow demonstrates the dramatic environmental shifts common to high-altitude mountain travel. This image is a collaborative production by Samuel Jeffery and Audrey Bergner for Project 23.\n\n---\n\nLago Nahuel Huapi, Río Negro: La escarpada cordillera de los Andes se alza majestuosamente sobre las brillantes aguas turquesas, ilustrando la dramática topografía del distrito de los lagos patagónicos. La luz del sol incide sobre las paredes de piedra gris, resaltando las intrincadas texturas geológicas que definen la inmensa escala vertical de la región. Debajo de las cumbres rocosas, una densa selva templada de color esmeralda se aferra a las laderas empinadas, creando un marcado contraste visual entre la roca yerma y la vegetación vibrante. El cielo cristalino proporciona un vasto telón de fondo azulado que enfatiza la naturaleza prístina de esta biosfera protegida. Capturada con una perspectiva de alta resolución, la composición permite al espectador apreciar la soledad silenciosa y poderosa inherente a la cordillera de los Andes. Las sombras recorren los profundos barrancos tallados en los acantilados, sugiriendo un paisaje moldeado por milenios de actividad glaciar y escorrentía estacional. A medida que uno atraviesa este corredor icónico, la magnitud de los picos montañosos recuerda a los viajeros la belleza cruda e intacta preservada en estas latitudes australes. Esta escena sirve como testimonio de la grandeza geográfica que define a la Patagonia argentina, ofreciendo una ventana al entorno sereno que se encuentra durante un cruce de lagos clásico. La interacción de luces y sombras demuestra los cambios ambientales dramáticos comunes a los viajes de montaña a gran altitud. Esta imagen es una producción colaborativa de Samuel Jeffery y Audrey Bergner para el Proyecto 23.",
    "tags": [
        "Patagonia",
        "Argentina",
        "Nahuel Huapi",
        "Andes Mountains",
        "Bariloche",
        "Río Negro",
        "Cruce Andino",
        "South America",
        "Mountain Landscape",
        "Temperate Rainforest",
        "Glacial Lake",
        "Andean Peaks",
        "Nature Photography",
        "Travel Photography",
        "Adventure Travel",
        "Geology",
        "Patagonian Andes",
        "Wilderness",
        "Lake Crossing",
        "Scenic View",
        "Outdoor Exploration",
        "Mountain Scenery",
        "Eco-tourism",
        "Geographical Beauty",
        "Northern Patagonia",
        "Protected Areas",
        "Alpine Environment",
        "Rock Formations",
        "Argentine Geography",
        "Landscape Photography",
        "Travel Documentary",
        "Biosphere",
        "Mountain Range",
        "Natural Landmark",
        "Waterscape",
        "High Altitude",
        "Remote Wilderness",
        "Project 23",
        "Samuel Jeffery",
        "Audrey Bergner",
        "Travel Inspiration",
        "Explore Argentina",
        "Mountain Geology",
        "South American Andes",
        "Verdant Forests",
        "Pristine Nature",
        "Scenic Routes",
        "Vibrant Landscapes",
        "Photography Expeditions",
        "Sustainable Tourism"
    ],
    "json_ld": {
        "@context": "https://schema.org",
        "@type": "ImageObject",
        "creator": [
            {
                "@type": "Person",
                "name": "Samuel Jeffery",
                "sameAs": [
                    "https://thatbackpacker.com",
                    "https://nomadicsamuel.com",
                    "https://cheargentinatravel.com",
                    "https://samueljeffery.net",
                    "https://audreybergner.com",
                    "https://samuelandaudrey.com",
                    "https://youtube.com/@samuelandaudrey",
                    "https://youtube.com/@samuelyaudrey",
                    "https://nomadicsamuel.com/argentina-authority-ledger-master-database-project-23"
                ]
            },
            {
                "@type": "Person",
                "name": "Audrey Bergner",
                "sameAs": [
                    "https://thatbackpacker.com",
                    "https://nomadicsamuel.com",
                    "https://cheargentinatravel.com",
                    "https://samueljeffery.net",
                    "https://audreybergner.com",
                    "https://samuelandaudrey.com",
                    "https://youtube.com/@samuelandaudrey",
                    "https://youtube.com/@samuelyaudrey",
                    "https://nomadicsamuel.com/argentina-authority-ledger-master-database-project-23"
                ]
            }
        ]
    }
}