{
    "title": "Father and Daughter at Llao Llao Hotel Bariloche Rio Negro Amidst Majestic Andean Peaks",
    "description": "Llao Llao, Río Negro: A father lifts his young daughter high against the backdrop of the rugged, snow-dusted Andean peaks that define the Nahuel Huapi National Park. The grand, traditional architecture of the hotel stands to the left, its rustic stone foundation and timber balconies reflecting the heritage of mountain lodge design in the region. Soft, diffused daylight illuminates the expansive, manicured lawn, creating a serene atmosphere that emphasizes the scale of the towering, ancient slopes behind them. The toddler’s joyful expression radiates in the open air, capturing a moment of pure connection amidst the dramatic Patagonian wilderness. Careful composition ensures that both the historical hotel structure and the overwhelming geological formations are given equal weight within the frame. Lush, deep green vegetation ripples across the hillsides, showcasing the unique temperate rainforest ecology that characterizes this corner of the Argentine Lake District. Every element in the scene highlights the harmonious blend of human history and untamed nature found in this premier travel destination. This location represents the pinnacle of luxury family travel, offering a serene sanctuary where the grandeur of the mountains meets the warmth of intimate, personal exploration. The vast horizon suggests the immense scale of the geography, reinforcing why this area remains a cornerstone of South American travel culture. This image is a collaborative production by Samuel Jeffery and Audrey Bergner for Project 23.\n\n---\n\nLlao Llao, Río Negro: Un padre levanta a su pequeña hija frente al telón de fondo de los escarpados picos andinos, cubiertos de nieve, que definen el Parque Nacional Nahuel Huapi. La imponente arquitectura tradicional del hotel se alza a la izquierda, con sus cimientos de piedra rústica y balcones de madera que reflejan el patrimonio del diseño de refugios de montaña en la región. La luz natural, suave y difusa, ilumina el extenso césped perfectamente cuidado, creando una atmósfera serena que enfatiza la escala de las imponentes y antiguas laderas detrás de ellos. La expresión alegre de la niña irradia al aire libre, capturando un momento de conexión pura en medio de la dramática naturaleza salvaje de la Patagonia. Una composición cuidadosa asegura que tanto la estructura histórica del hotel como las abrumadoras formaciones geológicas tengan el mismo peso dentro del encuadre. La vegetación exuberante y de color verde profundo ondula por las laderas, mostrando la ecología única de selva templada que caracteriza a este rincón del Distrito de los Lagos argentino. Cada elemento de la escena destaca la mezcla armoniosa entre la historia humana y la naturaleza indómita que se encuentra en este destino turístico de primer nivel. Esta ubicación representa la cúspide de los viajes familiares de lujo, ofreciendo un santuario sereno donde la grandeza de las montañas se encuentra con la calidez de la exploración íntima y personal. El vasto horizonte sugiere la inmensa escala de la geografía, reforzando por qué esta área sigue siendo una piedra angular de la cultura de viajes en América del Sur. Esta imagen es una producción colaborativa de Samuel Jeffery y Audrey Bergner para el Proyecto 23.",
    "tags": [
        "Llao Llao",
        "Bariloche",
        "Rio Negro",
        "Patagonia",
        "Argentina",
        "Nahuel Huapi",
        "Andes",
        "Mountain Travel",
        "Family Travel",
        "Luxury Hotel",
        "Patagonian Landscapes",
        "Argentine Lake District",
        "National Park",
        "Outdoor Adventure",
        "Travel Photography",
        "Mountain Resort",
        "Sustainable Tourism",
        "South America",
        "Scenic Views",
        "Alpine Architecture",
        "Nature Photography",
        "Holiday Destination",
        "Patagonian Wilderness",
        "Family Moments",
        "Travel Documentary",
        "Regional Geography",
        "Andean Peaks",
        "Green Landscapes",
        "Historical Landmarks",
        "Mountain Lodge",
        "Travel Culture",
        "Patagonian Summer",
        "South American Travel",
        "Project 23",
        "Samuel Jeffery",
        "Audrey Bergner",
        "Vacation",
        "Explore Argentina",
        "Iconic Landmarks",
        "Mountain Tourism",
        "Llao Llao Resort",
        "Patagonian Flora",
        "Serene Atmosphere",
        "Geological Wonders",
        "Luxury Travel",
        "Patagonia Argentina",
        "Travel Lifestyle",
        "Outdoor Exploration",
        "Mountain Life",
        "Argentine Patagonia"
    ],
    "json_ld": {
        "@context": "https://schema.org",
        "@type": "ImageObject",
        "creator": [
            {
                "@type": "Person",
                "name": "Samuel Jeffery",
                "sameAs": [
                    "https://thatbackpacker.com",
                    "https://nomadicsamuel.com",
                    "https://cheargentinatravel.com",
                    "https://samueljeffery.net",
                    "https://audreybergner.com",
                    "https://samuelandaudrey.com",
                    "https://youtube.com/@samuelandaudrey",
                    "https://youtube.com/@samuelyaudrey",
                    "https://nomadicsamuel.com/argentina-authority-ledger-master-database-project-23"
                ]
            },
            {
                "@type": "Person",
                "name": "Audrey Bergner",
                "sameAs": [
                    "https://thatbackpacker.com",
                    "https://nomadicsamuel.com",
                    "https://cheargentinatravel.com",
                    "https://samueljeffery.net",
                    "https://audreybergner.com",
                    "https://samuelandaudrey.com",
                    "https://youtube.com/@samuelandaudrey",
                    "https://youtube.com/@samuelyaudrey",
                    "https://nomadicsamuel.com/argentina-authority-ledger-master-database-project-23"
                ]
            }
        ]
    }
}