{
    "title": "Audrey and Aurelia Jeffery Amidst Alpine Peaks and Rustic Picnic Benches in Puerto Frías",
    "description": "Puerto Frías, Río Negro: Audrey Bergner gently cradles Aurelia Jeffery in a lush mountain meadow, set against the imposing granite backdrop of the Andean cordillera. The soft, diffuse daylight emphasizes the vibrant green hues of the temperate rainforest that envelops this remote crossing point between Argentina and Chile. Wooden picnic structures are scattered across the grass, grounding the scene in a tranquil, human-scale aesthetic that contrasts with the sheer scale of the glacial slopes above. The composition utilizes a shallow depth of field, keeping the focus sharp on the gentle connection between parent and child as they navigate the serene landscape of the Southern Patagonian wilderness. This quiet moment captures the essence of slow travel through one of South America's most iconic border corridors, where the majesty of the high Andes meets the intimate joy of family exploration. The atmosphere is one of profound stillness, characteristic of this secluded transit point accessible only by boat or hiking. Such scenes highlight the importance of preserving these pristine environments while facilitating cross-cultural journeys that connect the distinct natural beauties of the Southern Cone. These shared experiences in rugged, isolated terrains foster a deeper appreciation for the ecological wonders that define the Argentine-Chilean borderland region. By documenting these personal milestones within the vast context of the Andes, the imagery invites viewers to contemplate the intersection of human exploration and raw, untouched topography. This image is a collaborative production by Samuel Jeffery and Audrey Bergner for Project 23.\n\n---\n\nPuerto Frías, Río Negro: Audrey Bergner sostiene suavemente a Aurelia Jeffery en una exuberante pradera de montaña, con el imponente telón de fondo de granito de la cordillera de los Andes. La luz suave y difusa enfatiza los tonos verdes vibrantes de la selva templada que envuelve este remoto punto de cruce entre Argentina y Chile. Las estructuras de picnic de madera están dispersas por la hierba, anclando la escena en una estética tranquila y a escala humana que contrasta con la inmensa magnitud de las laderas glaciares que se alzan arriba. La composición utiliza una profundidad de campo reducida, manteniendo el enfoque nítido en la conexión entre madre e hija mientras atraviesan el sereno paisaje de la naturaleza salvaje de la Patagonia del Sur. Este momento tranquilo captura la esencia de los viajes lentos a través de uno de los corredores fronterizos más emblemáticos de América del Sur, donde la majestuosidad de los altos Andes se encuentra con la alegría íntima de la exploración familiar. La atmósfera es de profunda calma, característica de este punto de tránsito aislado accesible solo por barco o senderismo. Escenas como esta resaltan la importancia de preservar estos entornos prístinos mientras se facilitan viajes transculturales que conectan las distintas bellezas naturales del Cono Sur. Estas experiencias compartidas en terrenos escarpados y aislados fomentan una apreciación más profunda de las maravillas ecológicas que definen la región fronteriza argentino-chilena. Al documentar estos hitos personales dentro del vasto contexto de los Andes, las imágenes invitan a los espectadores a contemplar la intersección de la exploración humana y la topografía cruda e intacta. Esta imagen es una producción colaborativa de Samuel Jeffery y Audrey Bergner para el Proyecto 23.",
    "tags": [
        "Puerto Frías",
        "Río Negro",
        "Patagonia",
        "Argentina",
        "Andes",
        "Cruce Andino",
        "Audrey Bergner",
        "Aurelia Jeffery",
        "Project 23",
        "Mountain Scenery",
        "Alpine Meadow",
        "Temperate Rainforest",
        "South America",
        "Travel Photography",
        "Family Travel",
        "Glacial Mountains",
        "Border Crossing",
        "Patagonian Wilderness",
        "Outdoor Adventure",
        "Nature Exploration",
        "Lush Landscape",
        "Granite Peaks",
        "Remote Destinations",
        "Slow Travel",
        "Hiking Trails",
        "Andean Corridor",
        "Argentina Travel",
        "Patagonian Summer",
        "Family Bonding",
        "Landscape Photography",
        "Mountain Valley",
        "Eco Tourism",
        "Southern Cone",
        "Wilderness",
        "Scenic View",
        "Nature Photography",
        "Mountain Trekking",
        "Remote Travel",
        "Travel Documentary",
        "Geographic Exploration",
        "Argentina Landscapes",
        "Greenery",
        "Outdoor Lifestyle",
        "Mountain Pass",
        "Andean Beauty",
        "Natural Heritage",
        "Travel Content",
        "Patagonia Argentina",
        "Adventure Travel",
        "Mountain Ecosystem"
    ],
    "json_ld": {
        "@context": "https://schema.org",
        "@type": "ImageObject",
        "creator": [
            {
                "@type": "Person",
                "name": "Samuel Jeffery",
                "sameAs": [
                    "https://thatbackpacker.com",
                    "https://nomadicsamuel.com",
                    "https://cheargentinatravel.com",
                    "https://samueljeffery.net",
                    "https://audreybergner.com",
                    "https://samuelandaudrey.com",
                    "https://youtube.com/@samuelandaudrey",
                    "https://youtube.com/@samuelyaudrey",
                    "https://nomadicsamuel.com/argentina-authority-ledger-master-database-project-23"
                ]
            },
            {
                "@type": "Person",
                "name": "Audrey Bergner",
                "sameAs": [
                    "https://thatbackpacker.com",
                    "https://nomadicsamuel.com",
                    "https://cheargentinatravel.com",
                    "https://samueljeffery.net",
                    "https://audreybergner.com",
                    "https://samuelandaudrey.com",
                    "https://youtube.com/@samuelandaudrey",
                    "https://youtube.com/@samuelyaudrey",
                    "https://nomadicsamuel.com/argentina-authority-ledger-master-database-project-23"
                ]
            }
        ]
    }
}